tabpymigrate/__init__.py
tabpymigrate/config.py
tabpymigrate/mapping.py
tabpymigrate/tabpymigrate.py
tabpymigrate/tabpymigrate_download.py
tabpymigrate/tabpymigrate_publish.py
tabpymigrate-1.0.1.dist-info/METADATA
tabpymigrate-1.0.1.dist-info/WHEEL
tabpymigrate-1.0.1.dist-info/top_level.txt
tabpymigrate-1.0.1.dist-info/RECORD
