Metadata-Version: 2.1
Name: tabpymigrate
Version: 1.0.1
Summary: Python project to download and deploy objects to Tableau Server via REST API.
Author-email: Tableau <kavikag00@gmail.com>
Project-URL: repository, https://github.com/codespg/tabpymigrate
Classifier: Programming Language :: Python
Classifier: Programming Language :: Python :: 3
Classifier: Programming Language :: Python :: 3.7
Classifier: Programming Language :: Python :: 3.8
Classifier: Programming Language :: Python :: 3.9
Classifier: Programming Language :: Python :: 3.10
Requires-Python: >=3.7
Requires-Dist: defusedxml (>=0.7.1)
Requires-Dist: packaging (>=22.0)
Requires-Dist: requests (>=2.28)
Requires-Dist: urllib3 (~=1.26.8)
Requires-Dist: tableauserverclient
Requires-Dist: tableaudocumentapi
Provides-Extra: test
Requires-Dist: argparse ; extra == 'test'
Requires-Dist: black ; extra == 'test'
Requires-Dist: mock ; extra == 'test'
Requires-Dist: mypy ; extra == 'test'
Requires-Dist: pytest (>=7.0) ; extra == 'test'
Requires-Dist: pytest-subtests ; extra == 'test'
Requires-Dist: requests-mock (<2.0,>=1.0) ; extra == 'test'
